<annotation>
  <folder>VOC2014_instance/dog</folder>
  <filename>000000002400.jpg</filename>
  <source>
    <database>MS COCO 2014</database>
    <annotation>MS COCO 2014</annotation>
    <image>Flickr</image>
    <url>http://images.cocodataset.org/train2017/000000002400.jpg</url>
  </source>
  <size>
    <width>640</width>
    <height>427</height>
    <depth>3</depth>
  </size>
  <segmented>0</segmented>
  <object>
    <name>dog</name>
    <bndbox>
      <xmin>35.37</xmin>
      <ymin>209.47</ymin>
      <xmax>208.76</xmax>
      <ymax>423.40999999999997</ymax>
    </bndbox>
    <difficult>0</difficult>
  </object>
  <object>
    <name>dog</name>
    <bndbox>
      <xmin>465.66</xmin>
      <ymin>72.29</ymin>
      <xmax>622.03</xmax>
      <ymax>298.25</ymax>
    </bndbox>
    <difficult>0</difficult>
  </object>
  <object>
    <name>person</name>
    <bndbox>
      <xmin>147.77</xmin>
      <ymin>29.75</ymin>
      <xmax>315.69</xmax>
      <ymax>427.0</ymax>
    </bndbox>
    <difficult>0</difficult>
  </object>
  <object>
    <name>clock</name>
    <bndbox>
      <xmin>257.9</xmin>
      <ymin>168.25</ymin>
      <xmax>269.44</xmax>
      <ymax>188.49</ymax>
    </bndbox>
    <difficult>0</difficult>
  </object>
  <object>
    <name>bench</name>
    <bndbox>
      <xmin>240.43</xmin>
      <ymin>142.33</ymin>
      <xmax>505.86</xmax>
      <ymax>415.46000000000004</ymax>
    </bndbox>
    <difficult>0</difficult>
  </object>
</annotation>
