<annotation>
  <folder>VOC2014_instance/horse</folder>
  <filename>000000004741.jpg</filename>
  <source>
    <database>MS COCO 2014</database>
    <annotation>MS COCO 2014</annotation>
    <image>Flickr</image>
    <url>http://images.cocodataset.org/train2017/000000004741.jpg</url>
  </source>
  <size>
    <width>640</width>
    <height>640</height>
    <depth>3</depth>
  </size>
  <segmented>0</segmented>
  <object>
    <name>horse</name>
    <bndbox>
      <xmin>284.75</xmin>
      <ymin>437.84</ymin>
      <xmax>469.98</xmax>
      <ymax>617.54</ymax>
    </bndbox>
    <difficult>0</difficult>
  </object>
  <object>
    <name>person</name>
    <bndbox>
      <xmin>326.55</xmin>
      <ymin>355.52</ymin>
      <xmax>402.24</xmax>
      <ymax>522.5699999999999</ymax>
    </bndbox>
    <difficult>0</difficult>
  </object>
  <object>
    <name>person</name>
    <bndbox>
      <xmin>107.08</xmin>
      <ymin>429.55</ymin>
      <xmax>132.34</xmax>
      <ymax>523.58</ymax>
    </bndbox>
    <difficult>0</difficult>
  </object>
  <object>
    <name>person</name>
    <bndbox>
      <xmin>62.42</xmin>
      <ymin>421.74</ymin>
      <xmax>88.43</xmax>
      <ymax>519.15</ymax>
    </bndbox>
    <difficult>0</difficult>
  </object>
  <object>
    <name>person</name>
    <bndbox>
      <xmin>122.37</xmin>
      <ymin>414.04</ymin>
      <xmax>138.89000000000001</xmax>
      <ymax>517.3000000000001</ymax>
    </bndbox>
    <difficult>0</difficult>
  </object>
  <object>
    <name>person</name>
    <bndbox>
      <xmin>74.43</xmin>
      <ymin>424.51</ymin>
      <xmax>116.38000000000001</xmax>
      <ymax>535.03</ymax>
    </bndbox>
    <difficult>0</difficult>
  </object>
</annotation>
