<annotation>
  <folder>VOC2014_instance/bus</folder>
  <filename>000000008204.jpg</filename>
  <source>
    <database>MS COCO 2014</database>
    <annotation>MS COCO 2014</annotation>
    <image>Flickr</image>
    <url>http://images.cocodataset.org/train2017/000000008204.jpg</url>
  </source>
  <size>
    <width>640</width>
    <height>480</height>
    <depth>3</depth>
  </size>
  <segmented>0</segmented>
  <object>
    <name>bus</name>
    <bndbox>
      <xmin>345.17</xmin>
      <ymin>269.66</ymin>
      <xmax>640.0</xmax>
      <ymax>473.53000000000003</ymax>
    </bndbox>
    <difficult>0</difficult>
  </object>
  <object>
    <name>person</name>
    <bndbox>
      <xmin>182.55</xmin>
      <ymin>377.36</ymin>
      <xmax>213.9</xmax>
      <ymax>426.96000000000004</ymax>
    </bndbox>
    <difficult>0</difficult>
  </object>
  <object>
    <name>person</name>
    <bndbox>
      <xmin>321.54</xmin>
      <ymin>379.78</ymin>
      <xmax>338.64000000000004</xmax>
      <ymax>458.09</ymax>
    </bndbox>
    <difficult>0</difficult>
  </object>
  <object>
    <name>person</name>
    <bndbox>
      <xmin>443.11</xmin>
      <ymin>354.54</ymin>
      <xmax>457.78000000000003</xmax>
      <ymax>367.85</ymax>
    </bndbox>
    <difficult>0</difficult>
  </object>
  <object>
    <name>person</name>
    <bndbox>
      <xmin>437.81</xmin>
      <ymin>358.71</ymin>
      <xmax>456.05</xmax>
      <ymax>375.26</ymax>
    </bndbox>
    <difficult>0</difficult>
  </object>
  <object>
    <name>person</name>
    <bndbox>
      <xmin>449.7</xmin>
      <ymin>353.43</ymin>
      <xmax>458.68</xmax>
      <ymax>364.19</ymax>
    </bndbox>
    <difficult>0</difficult>
  </object>
  <object>
    <name>truck</name>
    <bndbox>
      <xmin>1.09</xmin>
      <ymin>138.23</ymin>
      <xmax>336.33</xmax>
      <ymax>476.73</ymax>
    </bndbox>
    <difficult>0</difficult>
  </object>
  <object>
    <name>handbag</name>
    <bndbox>
      <xmin>326.83</xmin>
      <ymin>423.95</ymin>
      <xmax>340.77</xmax>
      <ymax>449.65999999999997</ymax>
    </bndbox>
    <difficult>0</difficult>
  </object>
  <object>
    <name>person</name>
    <bndbox>
      <xmin>483.97</xmin>
      <ymin>364.11</ymin>
      <xmax>494.22</xmax>
      <ymax>374.86</ymax>
    </bndbox>
    <difficult>0</difficult>
  </object>
  <object>
    <name>person</name>
    <bndbox>
      <xmin>553.56</xmin>
      <ymin>361.44</ymin>
      <xmax>567.17</xmax>
      <ymax>374.79</ymax>
    </bndbox>
    <difficult>0</difficult>
  </object>
  <object>
    <name>person</name>
    <bndbox>
      <xmin>597.69</xmin>
      <ymin>356.18</ymin>
      <xmax>609.72</xmax>
      <ymax>375.55</ymax>
    </bndbox>
    <difficult>0</difficult>
  </object>
  <object>
    <name>person</name>
    <bndbox>
      <xmin>128.34</xmin>
      <ymin>350.57</ymin>
      <xmax>165.36</xmax>
      <ymax>441.85</ymax>
    </bndbox>
    <difficult>0</difficult>
  </object>
  <object>
    <name>person</name>
    <bndbox>
      <xmin>538.11</xmin>
      <ymin>361.19</ymin>
      <xmax>550.28</xmax>
      <ymax>377.3</ymax>
    </bndbox>
    <difficult>0</difficult>
  </object>
  <object>
    <name>person</name>
    <bndbox>
      <xmin>470.34</xmin>
      <ymin>342.19</ymin>
      <xmax>477.26</xmax>
      <ymax>355.04</ymax>
    </bndbox>
    <difficult>0</difficult>
  </object>
  <object>
    <name>handbag</name>
    <bndbox>
      <xmin>324.69</xmin>
      <ymin>416.58</ymin>
      <xmax>331.37</xmax>
      <ymax>424.19</ymax>
    </bndbox>
    <difficult>0</difficult>
  </object>
  <object>
    <name>person</name>
    <bndbox>
      <xmin>433.18</xmin>
      <ymin>360.93</ymin>
      <xmax>445.65000000000003</xmax>
      <ymax>377.62</ymax>
    </bndbox>
    <difficult>0</difficult>
  </object>
  <object>
    <name>person</name>
    <bndbox>
      <xmin>466.51</xmin>
      <ymin>351.0</ymin>
      <xmax>479.59999999999997</xmax>
      <ymax>368.14</ymax>
    </bndbox>
    <difficult>0</difficult>
  </object>
  <object>
    <name>person</name>
    <bndbox>
      <xmin>265</xmin>
      <ymin>368</ymin>
      <xmax>480</xmax>
      <ymax>439</ymax>
    </bndbox>
    <difficult>1</difficult>
  </object>
</annotation>
